{
	"version": 1,
	"named_parameters": true,
	"parameters": [
		{
			"id": "x52gWS7EBuAj6nGG",
			"name": "result_prefix",
			"param_name": "result_prefix",
			"description": "\"project level\" name of data folder",
			"type": "text",
			"value_type": "string",
			"required": true
		},
		{
			"id": "uxoZwW2rMVHw8rAt",
			"name": "run_id",
			"param_name": "run_id",
			"description": "A unique suffix that should be used for all decoding runs within a parameter sweep - defaults to datetime",
			"type": "text",
			"value_type": "string"
		},
		{
			"id": "rj6ETIWbYoQJsMqM",
			"name": "logging_level",
			"param_name": "logging_level",
			"description": "DEBUG, INFO, WARNING, ERROR",
			"type": "text",
			"value_type": "string",
			"default_value": "INFO"
		},
		{
			"id": "5Lq8N5fGlmWi7M3Z",
			"name": "override_params_json",
			"param_name": "override_params_json",
			"description": "A json string of parameters to pass to Params class. Keys must be fields on Params class. Overrides values specified individually in App Builder",
			"type": "text",
			"value_type": "string",
			"default_value": "{}"
		},
		{
			"id": "CKVquiTjW2bADhJk",
			"name": "test",
			"param_name": "test",
			"description": "Run the capsule in test mode, which should finish quickly",
			"type": "text",
			"value_type": "integer",
			"default_value": "0",
			"maximum": 1
		},
		{
			"id": "SwennXmUnO9E9T0D",
			"name": "update_packages_from_source",
			"param_name": "update_packages_from_source",
			"description": "If 1, auto-updates package(s) (e.g.  dynamic-routing-analysis) on each run. Disable for quicker testing",
			"type": "text",
			"value_type": "integer",
			"default_value": "1",
			"maximum": 1
		},
		{
			"id": "exDAGscNDd2rht1z",
			"name": "decoder_type",
			"param_name": "decoder_type",
			"type": "text",
			"value_type": "string",
			"default_value": "LogisticRegression"
		},
		{
			"id": "HfnBe3exbfyVCqyC",
			"name": "feature_intervals",
			"param_name": "feature_intervals",
			"type": "text",
			"value_type": "string",
			"default_value": "quiescent"
		}
	]
}