{
	"version": 1,
	"named_parameters": true,
	"parameters": [
		{
			"id": "x52gWS7EBuAj6nGG",
			"name": "result_prefix",
			"param_name": "result_prefix",
			"description": "\"project level\" name of data folder",
			"type": "text",
			"value_type": "string",
			"required": true
		},
		{
			"id": "uxoZwW2rMVHw8rAt",
			"name": "run_id",
			"param_name": "run_id",
			"description": "A unique suffix that should be used for all decoding runs within a parameter sweep - defaults to datetime",
			"type": "text",
			"value_type": "string"
		},
		{
			"id": "xxVUgdPR32dB7B9H",
			"name": "session_id",
			"param_name": "session_id",
			"description": "Provide a single session ID \u003csubjectID\u003e_\u003cyyyy-mm-dd\u003e (default empty: run for all sessions in datacube)",
			"type": "text",
			"value_type": "string"
		},
		{
			"id": "rj6ETIWbYoQJsMqM",
			"name": "logging_level",
			"param_name": "logging_level",
			"description": "DEBUG, INFO, WARNING, ERROR",
			"type": "text",
			"value_type": "string",
			"default_value": "INFO"
		},
		{
			"id": "u68UC9mfe9wxpOzc",
			"name": "unit_criteria",
			"param_name": "unit_criteria",
			"type": "text",
			"value_type": "string",
			"default_value": "no_drift"
		},
		{
			"id": "TodaD5cDUuK1OCzO",
			"name": "n_units",
			"param_name": "n_units",
			"type": "text",
			"value_type": "string",
			"default_value": "all"
		},
		{
			"id": "CLnGBLMVID8fEr6c",
			"name": "session_table_query",
			"param_name": "session_table_query",
			"description": "Query text to pass to df.query(), for filtering session_table (sessions excluded by filter are not processed)",
			"type": "text",
			"value_type": "string",
			"default_value": "is_ephys \u0026 is_task \u0026 is_annotated \u0026 is_production \u0026 issues=='[]'"
		},
		{
			"id": "5Lq8N5fGlmWi7M3Z",
			"name": "override_params_json",
			"param_name": "override_params_json",
			"description": "A json string of parameters to pass to Params class. Keys must be fields on Params class. Overrides values specified individually in App Builder",
			"type": "text",
			"value_type": "string",
			"default_value": "{}"
		},
		{
			"id": "9zeS6i4cLxdwWiVC",
			"name": "skip_existing",
			"param_name": "skip_existing",
			"type": "text",
			"value_type": "integer",
			"default_value": "1",
			"maximum": 1
		},
		{
			"id": "CKVquiTjW2bADhJk",
			"name": "test",
			"param_name": "test",
			"description": "Run the capsule in test mode, which should finish quickly",
			"type": "text",
			"value_type": "integer",
			"default_value": "1",
			"maximum": 1
		},
		{
			"id": "SwennXmUnO9E9T0D",
			"name": "update_packages_from_source",
			"param_name": "update_packages_from_source",
			"description": "If 1, auto-updates package(s) (e.g.  dynamic-routing-analysis) on each run. Disable for quicker testing",
			"type": "text",
			"value_type": "integer",
			"default_value": "1",
			"maximum": 1
		},
		{
			"id": "exDAGscNDd2rht1z",
			"name": "decoder_type",
			"param_name": "decoder_type",
			"type": "text",
			"value_type": "string",
			"default_value": "LogisticRegression"
		},
		{
			"id": "mEO7YbVSqdrSMD9O",
			"name": "use_process_pool",
			"param_name": "use_process_pool",
			"type": "text",
			"value_type": "integer",
			"default_value": "1",
			"maximum": 1
		},
		{
			"id": "RRWkAt4rHoxQdIYU",
			"name": "max_workers",
			"param_name": "max_workers",
			"type": "text",
			"value_type": "integer"
		},
		{
			"id": "QGCJSR6IiJRCG44R",
			"name": "n_jobs",
			"param_name": "n_jobs",
			"type": "text",
			"value_type": "integer"
		}
	]
}